{
   "ITEM": {
      "ITEM_INFO": {
         "rootquest": {
            "WHICHWORD": {
               "DRAG_DROP": "Miss Hoa: Good morning, children\nChildren: Good morning, Miss Hoa\nMiss Hoa: How are you?\nChildren: We're fine, thank you. How are you?\nMiss Hoa: Fine thank. Good bye.\nChildren: Bye",
               "EXTEND_DRAG": [
                  {
                     "data": "boy"
                  },
                  {
                     "data": "girl"
                  },
                  {
                     "data": "hot"
                  }
               ],
               "Title": "3. Select a suitable word",
               "Dapan": "24,32|62,66|78,81|114,123|161,169",
               "mediatype": "image",
               "mediaurl": ""
            }
         }
      },
      "APPEAR": {
         "id": "NoID",
         "name": "None",
         "direction": "None",
         "start": "Auto",
         "speed": "0",
         "repeat": "false",
         "index": "0"
      },
      "LINK": {
         "type": "none",
         "href": ""
      },
      "id": "4BD763BE-E976-C203-5590-3C746C52CD37",
      "name": "iDropList",
      "type": "module",
      "x": "33.5732395781786",
      "y": "49.8951605046049",
      "width": "336.011283859884",
      "height": "396.28356289965",
      "scaleX": "1",
      "scaleY": "1",
      "rotation": "0"
   }
}